flumine/__init__.py
flumine/__version__.py
flumine/baseflumine.py
flumine/config.py
flumine/exceptions.py
flumine/flumine.py
flumine/patching.py
flumine/utils.py
flumine/worker.py
flumine/clients/__init__.py
flumine/clients/baseclient.py
flumine/clients/betconnectclient.py
flumine/clients/betdaqclient.py
flumine/clients/betfairclient.py
flumine/clients/clients.py
flumine/clients/simulatedclient.py
flumine/controls/__init__.py
flumine/controls/clientcontrols.py
flumine/controls/loggingcontrols.py
flumine/controls/tradingcontrols.py
flumine/events/__init__.py
flumine/events/events.py
flumine/execution/__init__.py
flumine/execution/baseexecution.py
flumine/execution/betdaqexecution.py
flumine/execution/betfairexecution.py
flumine/execution/simulatedexecution.py
flumine/execution/transaction.py
flumine/markets/__init__.py
flumine/markets/blotter.py
flumine/markets/market.py
flumine/markets/markets.py
flumine/markets/middleware.py
flumine/order/__init__.py
flumine/order/order.py
flumine/order/orderpackage.py
flumine/order/ordertype.py
flumine/order/process.py
flumine/order/responses.py
flumine/order/trade.py
flumine/simulation/__init__.py
flumine/simulation/simulatedorder.py
flumine/simulation/simulation.py
flumine/simulation/utils.py
flumine/strategy/__init__.py
flumine/strategy/runnercontext.py
flumine/strategy/strategy.py
flumine/streams/__init__.py
flumine/streams/basestream.py
flumine/streams/betdaqorderpolling.py
flumine/streams/datastream.py
flumine/streams/historicalstream.py
flumine/streams/marketstream.py
flumine/streams/orderstream.py
flumine/streams/simulatedorderstream.py
flumine/streams/sportsdatastream.py
flumine/streams/streams.py
flumine-2.11.5.dist-info/METADATA
flumine-2.11.5.dist-info/WHEEL
flumine-2.11.5.dist-info/licenses/LICENSE
flumine-2.11.5.dist-info/RECORD
