Metadata-Version: 2.4
Name: flumine
Version: 2.11.5
Summary: Betting trading framework
Project-URL: Homepage, https://github.com/betcode-org
Project-URL: Documentation, https://betcode-org.github.io/flumine/
Project-URL: Repository, https://github.com/betcode-org/flumine.git
Project-URL: Bug Tracker, https://github.com/betcode-org/flumine/issues
Project-URL: Changelog, https://github.com/betcode-org/flumine/blob/master/HISTORY.rst
Author-email: Liam Pauling <a@unknown.com>
License: MIT License
License-File: LICENSE
Classifier: License :: OSI Approved :: MIT License
Classifier: Operating System :: OS Independent
Classifier: Programming Language :: Python :: 3.9
Classifier: Programming Language :: Python :: 3.10
Classifier: Programming Language :: Python :: 3.11
Classifier: Programming Language :: Python :: 3.12
Classifier: Programming Language :: Python :: 3.13
Classifier: Programming Language :: Python :: 3.14
Requires-Python: >=3.9
Requires-Dist: betconnect==0.3.0
Requires-Dist: betdaq-retail==0.2.0
Requires-Dist: betfairlightweight==2.22.1
Requires-Dist: python-json-logger==2.0.7
Requires-Dist: requests
Requires-Dist: smart-open<8,>=6
Requires-Dist: tenacity<8.3.1,>=7.0.0
Provides-Extra: speed
Requires-Dist: betfairlightweight[speed]==2.22.1; extra == 'speed'
Provides-Extra: test
Requires-Dist: black==25.1.0; extra == 'test'
Requires-Dist: build; extra == 'test'
Requires-Dist: coverage; extra == 'test'
Requires-Dist: mkdocs; extra == 'test'
Requires-Dist: mkdocs-material; extra == 'test'
Requires-Dist: pre-commit; extra == 'test'
Requires-Dist: twine; extra == 'test'
